sexsmith_suite/__init__.py
sexsmith_suite/core.py
sexsmith_suite-0.0.3.dist-info/METADATA
sexsmith_suite-0.0.3.dist-info/WHEEL
sexsmith_suite-0.0.3.dist-info/licenses/LICENSE
sexsmith_suite-0.0.3.dist-info/RECORD
